LICENSE
MANIFEST.in
README.md
setup.py
pyquerystring/__init__.py
pyquerystring/compat.py
pyquerystring/querystring.py
pyquerystring.egg-info/PKG-INFO
pyquerystring.egg-info/SOURCES.txt
pyquerystring.egg-info/dependency_links.txt
pyquerystring.egg-info/pbr.json
pyquerystring.egg-info/top_level.txt