Metadata-Version: 1.1
Name: pyquerystring
Version: 1.0.1
Summary: Query String Parsing The Way It Should Be
Home-page: http://github.com/aventurella/pyquerystring
Author: Adam Venturella
Author-email: aventurella@gmail.com
License: Fancy query string parsing & application/x-www-form-urlencoded parsing
